graph_serialization/__init__.py
graph_serialization/app_metrics.py
graph_serialization/app_serialization.py
graph_serialization/connector_config.py
graph_serialization/flow_metrics.py
graph_serialization/flow_serialization.py
mule_graph-0.0.1.dist-info/METADATA
mule_graph-0.0.1.dist-info/WHEEL
mule_graph-0.0.1.dist-info/top_level.txt
mule_graph-0.0.1.dist-info/RECORD
