Metadata-Version: 2.1
Name: mule-graph
Version: 0.0.1
Summary: small graph representation library for muleapp
Home-page: UNKNOWN
Author: levensworth
Author-email: sbassani@mulesoft.com
License: UNKNOWN
Platform: UNKNOWN
Classifier: Programming Language :: Python :: 3
Requires-Python: >=3.5
